matplotlib_scalebar/__init__.py
matplotlib_scalebar/_version.py
matplotlib_scalebar/dimension.py
matplotlib_scalebar/scalebar.py
matplotlib_scalebar/test_dimension.py
matplotlib_scalebar/test_scalebar.py
matplotlib_scalebar-0.8.1.dist-info/LICENSE
matplotlib_scalebar-0.8.1.dist-info/METADATA
matplotlib_scalebar-0.8.1.dist-info/WHEEL
matplotlib_scalebar-0.8.1.dist-info/top_level.txt
matplotlib_scalebar-0.8.1.dist-info/zip-safe
matplotlib_scalebar-0.8.1.dist-info/RECORD
