Metadata-Version: 2.1
Name: matplotlib-scalebar
Version: 0.8.1
Summary: Artist for matplotlib to display a scale bar
Home-page: https://github.com/ppinard/matplotlib-scalebar
Author: Philippe Pinard
Author-email: philippe.pinard@gmail.com
Maintainer: Philippe Pinard
Maintainer-email: philippe.pinard@gmail.com
License: BSD
Keywords: matplotlib scale micron bar
Platform: UNKNOWN
Classifier: Development Status :: 4 - Beta
Classifier: Intended Audience :: Science/Research
Classifier: License :: OSI Approved :: BSD License
Classifier: Operating System :: OS Independent
Classifier: Programming Language :: Python :: 3
Classifier: Programming Language :: Python :: 3.7
Classifier: Programming Language :: Python :: 3.8
Classifier: Programming Language :: Python :: 3.9
Classifier: Programming Language :: Python :: 3.10
Classifier: Topic :: Scientific/Engineering :: Visualization
Requires-Python: ~=3.7
License-File: LICENSE
